AUTHORS
INSTALL
LICENSE
MANIFEST.in
NOTICE
README
requirements.txt
setup.cfg
setup.py
docs/Makefile
docs/conf.py
docs/configuration.rst
docs/faq.rst
docs/index.rst
docs/installation.rst
docs/introduction.rst
docs/make.bat
docs/usage.rst
src/django_traxauth.egg-info/PKG-INFO
src/django_traxauth.egg-info/SOURCES.txt
src/django_traxauth.egg-info/dependency_links.txt
src/django_traxauth.egg-info/top_level.txt
src/traxauth/__init__.py
src/traxauth/forms.py
src/traxauth/models.py
src/traxauth/settings.py
src/traxauth/tests.py
src/traxauth/urls.py
src/traxauth/utils.py
src/traxauth/views.py
src/traxauth/media/traxauth/css/style.css
src/traxauth/registration_backend/__init__.py
src/traxauth/registration_backend/forms.py
src/traxauth/registration_backend/urls.py
src/traxauth/registration_backend/views.py
src/traxauth/templates/profiles/create_profile.html
src/traxauth/templates/profiles/edit_profile.html
src/traxauth/templates/profiles/profile_detail.html
src/traxauth/templates/profiles/profile_list.html
src/traxauth/templates/registration/activate.html
src/traxauth/templates/registration/activation_complete.html
src/traxauth/templates/registration/login.html
src/traxauth/templates/registration/logout.html
src/traxauth/templates/registration/password_change_form.html
src/traxauth/templates/registration/password_complete.html
src/traxauth/templates/registration/password_reset_complete.html
src/traxauth/templates/registration/password_reset_confirm.html
src/traxauth/templates/registration/password_reset_done.html
src/traxauth/templates/registration/password_reset_email.html
src/traxauth/templates/registration/password_reset_form.html
src/traxauth/templates/registration/registration_closed.html
src/traxauth/templates/registration/registration_complete.html
src/traxauth/templates/registration/registration_form.html
src/traxauth/templates/traxauth/base.html
src/traxauth/templates/traxauth/gravatar.html
src/traxauth/templatetags/__init__.py
src/traxauth/templatetags/traxauth_tags.py